Metadata-Version: 2.1
Name: django-http-last-modified-view
Version: 2020.7.1
Summary: Django http Last-Modified header view mixin
Home-page: https://github.com/andrewp-as-is/django-http-last-modified-view.py
License: Unlicense
Keywords: django Last-Modified header view
Platform: UNKNOWN
Classifier: Framework :: Django
Classifier: License :: Public Domain
Classifier: Operating System :: OS Independent
Classifier: Programming Language :: Python :: 3
